teamux/__init__.py
teamux/base.py
teamux/context.py
teamux/pane.py
teamux/session.py
teamux/tmux.py
teamux/window.py
teamux-0.2413.0.dist-info/METADATA
teamux-0.2413.0.dist-info/WHEEL
teamux-0.2413.0.dist-info/top_level.txt
teamux-0.2413.0.dist-info/RECORD
